{
  "active_tokens": 16,
  "batch_size": 2,
  "candidate": "issue-47-candidate-1",
  "device": "cpu",
  "dtype": "int64",
  "elapsed_ms": "4.5607",
  "mode": "both",
  "notes": "use_cache_passed=True;detached_outputs=True;hidden_dim=32;vocab_size=128;torch=2.7.1+cu126;cuda_available=True;cuda=12.6;gpu=NVIDIA GeForce RTX 3050",
  "paged_kv_baseline_mb": "",
  "peak_allocated_mb": "",
  "peak_reserved_mb": "",
  "seq_len": 16,
  "stage": "evaluation",
  "status": "pass",
  "timestamp": "2026-06-03T13:15:23.584618+00:00"
}